napari_kldeconv/__init__.py
napari_kldeconv/_reader.py
napari_kldeconv/_sample_data.py
napari_kldeconv/_version.py
napari_kldeconv/_widget.py
napari_kldeconv/_writer.py
napari_kldeconv/napari.yaml
napari_kldeconv/_tests/__init__.py
napari_kldeconv/_tests/test_reader.py
napari_kldeconv/_tests/test_sample_data.py
napari_kldeconv/_tests/test_widget.py
napari_kldeconv/_tests/test_writer.py
napari_kldeconv-0.1.0.dist-info/licenses/LICENSE
napari_kldeconv-0.1.0.dist-info/METADATA
napari_kldeconv-0.1.0.dist-info/WHEEL
napari_kldeconv-0.1.0.dist-info/entry_points.txt
napari_kldeconv-0.1.0.dist-info/top_level.txt
napari_kldeconv-0.1.0.dist-info/RECORD
