Metadata-Version: 2.4
Name: napari-kldeconv
Version: 0.1.0
Summary: A napari plugin for using KLDeconv algorithm.
Author: Qiqi Lu
Author-email: 136303971@qq.com
License: 
Project-URL: Bug Tracker, https://github.com/qiqi-lu/napari-kldeconv/issues
Project-URL: Documentation, https://github.com/qiqi-lu/napari-kldeconv#README.md
Project-URL: Source Code, https://github.com/qiqi-lu/napari-kldeconv
Project-URL: User Support, https://github.com/qiqi-lu/napari-kldeconv/issues
Classifier: Development Status :: 2 - Pre-Alpha
Classifier: Framework :: napari
Classifier: Intended Audience :: Developers
Classifier: License :: OSI Approved :: MIT License
Classifier: Operating System :: OS Independent
Classifier: Programming Language :: Python
Classifier: Programming Language :: Python :: 3
Classifier: Programming Language :: Python :: 3 :: Only
Classifier: Programming Language :: Python :: 3.10
Classifier: Programming Language :: Python :: 3.11
Classifier: Programming Language :: Python :: 3.12
Classifier: Programming Language :: Python :: 3.13
Classifier: Topic :: Scientific/Engineering :: Image Processing
Requires-Python: >=3.10
License-File: LICENSE
Requires-Dist: numpy
Requires-Dist: magicgui
Requires-Dist: qtpy
Requires-Dist: scikit-image
Provides-Extra: all
Requires-Dist: napari[all]; extra == "all"
Provides-Extra: testing
Requires-Dist: tox; extra == "testing"
Requires-Dist: pytest; extra == "testing"
Requires-Dist: pytest-cov; extra == "testing"
Requires-Dist: pytest-qt; extra == "testing"
Requires-Dist: napari[qt]; extra == "testing"
Dynamic: license-file
